fwatch/__init__.py
fwatch/__main__.py
fwatch/fwatch.py
fwatch-0.1.0.dist-info/WHEEL
fwatch-0.1.0.dist-info/entry_points.txt
fwatch-0.1.0.dist-info/METADATA
fwatch-0.1.0.dist-info/RECORD
