Metadata-Version: 2.1
Name: fwatch
Version: 0.1.0
Summary: A very simple file watcher.
Home-page: https://github.com/whonore/fwatch
License: MIT
Author: Wolf Honore
Author-email: wolfhonore@gmail.com
Requires-Python: >=3.8.1,<4.0.0
Classifier: License :: OSI Approved :: MIT License
Classifier: Programming Language :: Python :: 3
Classifier: Programming Language :: Python :: 3.9
Classifier: Programming Language :: Python :: 3.10
Classifier: Programming Language :: Python :: 3.11
Requires-Dist: pathspec (>=0.10.3,<0.11.0)
Project-URL: Repository, https://github.com/whonore/fwatch
